{
  "connection": "default",
  "collectionName": "comments",
  "info": {
    "name": "comment",
    "description": ""
  },
  "options": {
    "increments": true,
    "timestamps": true,
    "comment": ""
  },
  "attributes": {
    "content": {
      "default": "",
      "minLength": 1,
      "type": "text",
      "required": true
    },
    "writer": {
      "collection": "user",
      "via": "commentWrite",
      "plugin": "users-permissions"
    },
    "isVisible": {
      "default": false,
      "type": "boolean"
    },
    "hidingMessage": {
      "default": "",
      "type": "string"
    },
    "parent": {
      "collection": "comment",
      "via": "children"
    },
    "children": {
      "model": "comment",
      "via": "parent"
    },
    "usersLike": {
      "collection": "user",
      "via": "commentLike",
      "plugin": "users-permissions"
    },
    "usersDislike": {
      "collection": "user",
      "via": "commentDislike",
      "plugin": "users-permissions"
    }
  }
}